encrypted_field/__init__.py
encrypted_field/fields.py
tests/__init__.py
tests/models.py
tests/settings.py
tests/migrations/0001_initial.py
tests/migrations/0002_alter_mymodel_id_alter_mymodel2_id_alter_mymodel3_id_and_more.py
tests/migrations/__init__.py
django_encrypted_field-1.0.4.dist-info/LICENSE
django_encrypted_field-1.0.4.dist-info/METADATA
django_encrypted_field-1.0.4.dist-info/WHEEL
django_encrypted_field-1.0.4.dist-info/top_level.txt
django_encrypted_field-1.0.4.dist-info/RECORD
