Metadata-Version: 2.1
Name: django-encrypted-field
Version: 1.0.4
Summary: This is a Django Model Field class that can be encrypted using ChaCha20 poly 1305, and other algorithms.
Home-page: https://github.com/patowc/django-encrypted-field
Author: Román Ramírez
Author-email: rramirez@rootedcon.com
License: MIT
Platform: UNKNOWN
Classifier: Environment :: Web Environment
Classifier: Intended Audience :: Developers
Classifier: License :: OSI Approved :: MIT License
Classifier: Operating System :: OS Independent
Classifier: Programming Language :: Python
Classifier: Programming Language :: Python :: 3
Classifier: Programming Language :: Python :: 3.5
Classifier: Programming Language :: Python :: 3.6
Classifier: Programming Language :: Python :: 3.7
Classifier: Programming Language :: Python :: 3.8
Classifier: Programming Language :: Python :: 3.9
Classifier: Programming Language :: Python :: Implementation :: CPython
Classifier: Programming Language :: Python :: Implementation :: PyPy
Classifier: Framework :: Django
Requires-Dist: Django (>=4.0)
Requires-Dist: pycryptodomex (>=3.12.0)
